negeng/__init__.py
negeng/retry_tools.py
negeng-0.0.1.dist-info/LICENSE
negeng-0.0.1.dist-info/METADATA
negeng-0.0.1.dist-info/WHEEL
negeng-0.0.1.dist-info/top_level.txt
negeng-0.0.1.dist-info/RECORD
