Metadata-Version: 2.1
Name: negeng
Version: 0.0.1
Summary: Negative Engineering library for designing in the negative space
Author-email: Collin Meyer <collinmmeyer@gmail.com>
Maintainer-email: Collin Meyer <collinmmeyer@gmail.com>
License: Copyright 2024 Collin Meyer
Requires-Python: >=3.10
License-File: LICENSE
